flaskspot/__init__.py
flaskspot/helper.py
flaskspot-0.1.1.dist-info/LICENCE
flaskspot-0.1.1.dist-info/METADATA
flaskspot-0.1.1.dist-info/WHEEL
flaskspot-0.1.1.dist-info/entry_points.txt
flaskspot-0.1.1.dist-info/top_level.txt
flaskspot-0.1.1.dist-info/RECORD
