Metadata-Version: 2.1
Name: flaskspot
Version: 0.1.1
Summary: FlaskSpot provides Starter Kits for Flask.
Home-page: UNKNOWN
Author: Abhijeet Sonawane
Author-email: abhijeet.sonawane001@gmail.com
License: MIT
Keywords: flaskspot flaskproject flaskstarterkit
Platform: UNKNOWN
Classifier: License :: OSI Approved :: MIT License
Classifier: Programming Language :: Python :: 3
Classifier: Programming Language :: Python :: 3.6
Classifier: Programming Language :: Python :: 3.7
Classifier: Programming Language :: Python :: 3.8
Classifier: Programming Language :: Python :: 3.9
Requires-Dist: click (==7.1.2)
Requires-Dist: cookiecutter (==1.7.2)
Requires-Dist: colorama
